tests/test_decomposer.py
tests/__init__.py
trviz/utils.py
trviz/motif_aligner.py
trviz/main.py
trviz/motif_encoder.py
trviz/decomposer.py
trviz/visualizer.py
trviz/__init__.py
trviz/cy/decompose.pyx
trviz/cy/decompose.cpython-38-x86_64-linux-gnu.so
trviz/cy/__init__.py
trviz/cy/decompose.c
trviz-1.2.0.dist-info/METADATA
trviz-1.2.0.dist-info/WHEEL
trviz-1.2.0.dist-info/top_level.txt
trviz-1.2.0.dist-info/RECORD
trviz-1.2.0.dist-info/LICENSE.md
