Metadata-Version: 2.1
Name: trviz
Version: 1.2.0
Summary: A python library for decomposing and visualizing tandem repeat sequences
Home-page: https://github.com/Jong-hun-Park/trviz
Author: Jonghun Park
Author-email: jop002@ucsd.edu
License: UNKNOWN
Platform: UNKNOWN
Classifier: Programming Language :: Python :: 3.8
Classifier: Programming Language :: Python :: 3.9
Classifier: Programming Language :: Python :: 3.10
Classifier: License :: OSI Approved :: BSD License
Classifier: Operating System :: OS Independent
Requires-Python: >=3.8
Requires-Dist: matplotlib
Requires-Dist: numpy
Requires-Dist: biopython
Requires-Dist: scipy
Requires-Dist: distinctipy
